pyquant/__init__.py
pyquant/command_line.py
pyquant/cpeaks.cp38-win_amd64.pyd
pyquant/cpeaks.pyx
pyquant/cpeaks_wrapper.py
pyquant/logger.py
pyquant/peaks.py
pyquant/reader.py
pyquant/utils.py
pyquant/worker.py
pyquant/static/classifier.pickle
pyquant/static/pyquant_output.html
pyquant-0.4.3.data/scripts/pyQuant
tests/__init__.py
tests/config.py
tests/fixtures.py
tests/integration_convenience_params.py
tests/integration_full.py
tests/integration_isobaric_tags.py
tests/integration_manual.py
tests/integration_targeted_search.py
tests/mixins.py
tests/test_math.py
tests/test_peaks.py
tests/test_reader.py
tests/test_utils.py
tests/utils.py
pyquant-0.4.3.dist-info/LICENSE.txt
pyquant-0.4.3.dist-info/METADATA
pyquant-0.4.3.dist-info/WHEEL
pyquant-0.4.3.dist-info/entry_points.txt
pyquant-0.4.3.dist-info/top_level.txt
pyquant-0.4.3.dist-info/RECORD
